diffsptk/__init__.py
diffsptk/functional.py
diffsptk/signals.py
diffsptk/typing.py
diffsptk/version.py
diffsptk/modules/__init__.py
diffsptk/modules/acorr.py
diffsptk/modules/acr2csm.py
diffsptk/modules/alaw.py
diffsptk/modules/ap.py
diffsptk/modules/b2mc.py
diffsptk/modules/base.py
diffsptk/modules/c2acr.py
diffsptk/modules/c2mpir.py
diffsptk/modules/c2ndps.py
diffsptk/modules/cdist.py
diffsptk/modules/chroma.py
diffsptk/modules/cqt.py
diffsptk/modules/csm2acr.py
diffsptk/modules/dct.py
diffsptk/modules/decimate.py
diffsptk/modules/delay.py
diffsptk/modules/delta.py
diffsptk/modules/dequantize.py
diffsptk/modules/df2.py
diffsptk/modules/dfs.py
diffsptk/modules/dht.py
diffsptk/modules/drc.py
diffsptk/modules/dst.py
diffsptk/modules/dtw.py
diffsptk/modules/entropy.py
diffsptk/modules/excite.py
diffsptk/modules/f0eval.py
diffsptk/modules/fbank.py
diffsptk/modules/fftcep.py
diffsptk/modules/fftr.py
diffsptk/modules/flux.py
diffsptk/modules/frame.py
diffsptk/modules/freqt.py
diffsptk/modules/freqt2.py
diffsptk/modules/gammatone.py
diffsptk/modules/gmm.py
diffsptk/modules/gnorm.py
diffsptk/modules/griffin.py
diffsptk/modules/grpdelay.py
diffsptk/modules/hilbert.py
diffsptk/modules/hilbert2.py
diffsptk/modules/histogram.py
diffsptk/modules/ialaw.py
diffsptk/modules/ica.py
diffsptk/modules/icqt.py
diffsptk/modules/idct.py
diffsptk/modules/idht.py
diffsptk/modules/idst.py
diffsptk/modules/ifbank.py
diffsptk/modules/ifftr.py
diffsptk/modules/ifreqt2.py
diffsptk/modules/igammatone.py
diffsptk/modules/ignorm.py
diffsptk/modules/imdct.py
diffsptk/modules/imdst.py
diffsptk/modules/imglsadf.py
diffsptk/modules/imsvq.py
diffsptk/modules/interpolate.py
diffsptk/modules/ipnorm.py
diffsptk/modules/ipqmf.py
diffsptk/modules/is2par.py
diffsptk/modules/istft.py
diffsptk/modules/iulaw.py
diffsptk/modules/ivq.py
diffsptk/modules/lar2par.py
diffsptk/modules/lbg.py
diffsptk/modules/levdur.py
diffsptk/modules/linear_intpl.py
diffsptk/modules/lpc.py
diffsptk/modules/lpc2lsp.py
diffsptk-3.4.0.dist-info/METADATA
diffsptk-3.4.0.dist-info/WHEEL
diffsptk-3.4.0.dist-info/licenses/LICENSE
diffsptk-3.4.0.dist-info/RECORD
