Metadata-Version: 2.4
Name: diffsptk
Version: 3.4.0
Summary: Speech signal processing modules for machine learning
Project-URL: Homepage, https://sp-tk.sourceforge.net/
Project-URL: Documentation, https://sp-nitech.github.io/diffsptk/latest/
Project-URL: Source, https://github.com/sp-nitech/diffsptk
Author: SPTK Working Group
Maintainer-email: Takenori Yoshimura <takenori@sp.nitech.ac.jp>
License: Apache 2.0
License-File: LICENSE
Keywords: dsp,pytorch,signal processing,sptk
Classifier: License :: OSI Approved :: Apache Software License
Classifier: Programming Language :: Python
Classifier: Programming Language :: Python :: 3 :: Only
Classifier: Programming Language :: Python :: 3.10
Classifier: Programming Language :: Python :: 3.11
Classifier: Programming Language :: Python :: 3.12
Classifier: Programming Language :: Python :: 3.13
Requires-Python: >=3.10
Requires-Dist: numpy>=1.23.0
Requires-Dist: penn<1.0.0,>=0.0.1
Requires-Dist: pylstraight>=0.1.0
Requires-Dist: scipy>=1.12.0
Requires-Dist: soundfile>=0.10.2
Requires-Dist: torch>=2.3.1
Requires-Dist: torchaudio>=2.3.1
Requires-Dist: torchcomp<0.3.0,>=0.1.0
Requires-Dist: torchlpc<0.7.0,>=0.1.0
Requires-Dist: tqdm>=4.63.0
Requires-Dist: vector-quantize-pytorch>=1.14.9
Provides-Extra: dev
Requires-Dist: build; extra == 'dev'
Requires-Dist: codespell; extra == 'dev'
Requires-Dist: mdformat; extra == 'dev'
Requires-Dist: numpydoc; extra == 'dev'
Requires-Dist: pkginfo; extra == 'dev'
Requires-Dist: pydata-sphinx-theme; extra == 'dev'
Requires-Dist: pytest; extra == 'dev'
Requires-Dist: pytest-cov; extra == 'dev'
Requires-Dist: ruff; extra == 'dev'
Requires-Dist: sphinx; extra == 'dev'
Requires-Dist: twine; extra == 'dev'
